topsis/__init__.py
topsis/__main__.py
Topsis_Mritunjay_102003030-1.0.1.dist-info/LICENSE
Topsis_Mritunjay_102003030-1.0.1.dist-info/METADATA
Topsis_Mritunjay_102003030-1.0.1.dist-info/WHEEL
Topsis_Mritunjay_102003030-1.0.1.dist-info/entry_points.txt
Topsis_Mritunjay_102003030-1.0.1.dist-info/top_level.txt
Topsis_Mritunjay_102003030-1.0.1.dist-info/RECORD
