Metadata-Version: 2.1
Name: Topsis-Mritunjay-102003030
Version: 1.0.1
Summary: Topsis package for Multiple Criteria Decision Making problems(MCDM) problems
Home-page: https://github.com/mritunjay-07/Topsis-Mritunjay-102003030
Author: Mritunjay Dubey
Author-email: mdubey_be20@thapar.edu
License: MIT
Platform: UNKNOWN
Classifier: License :: OSI Approved :: MIT License
Classifier: Programming Language :: Python :: 3.6
Classifier: Programming Language :: Python :: 3.7
Classifier: Programming Language :: Python :: 3.8
Classifier: Programming Language :: Python :: 3.9
Classifier: Programming Language :: Python :: 3.10
Classifier: Programming Language :: Python :: 3.11
Classifier: Operating System :: OS Independent
Requires-Python: >=3.6
Requires-Dist: numpy
Requires-Dist: pandas
